{
  "generator-jhipster": {
    "authenticationType": "jwt",
    "cacheProvider": "ehcache",
    "serverPort": "8081",
    "serviceDiscoveryType": "eureka",
    "skipUserManagement": true,
    "baseName": "microProductos",
    "buildTool": "maven",
    "databaseType": "sql",
    "devDatabaseType": "mysql",
    "enableHibernateCache": true,
    "enableSwaggerCodegen": false,
    "enableTranslation": true,
    "jhiPrefix": "jhi",
    "languages": ["es", "en"],
    "messageBroker": false,
    "prodDatabaseType": "mysql",
    "searchEngine": false,
    "skipClient": true,
    "testFrameworks": [],
    "websocket": false,
    "enableGradleEnterprise": false,
    "gradleEnterpriseHost": "",
    "applicationType": "microservice",
    "packageName": "ar.edu.um.programacion2.micro_productos",
    "packageFolder": "ar/edu/um/programacion2/micro_productos",
    "nativeLanguage": "es",
    "jhipsterVersion": "7.3.0",
    "clientPackageManager": "npm",
    "dtoSuffix": "DTO",
    "entitySuffix": "",
    "reactive": false,
    "applicationIndex": 1,
    "gatewayServerPort": "9000",
    "skipServer": false,
    "skipCheckLengthOfIdentifier": false,
    "skipFakeData": false,
    "blueprints": [],
    "otherModules": [],
    "pages": [],
    "clientFramework": "angularX",
    "clientTheme": "none",
    "clientThemeVariant": "",
    "withAdminUi": false,
    "creationTimestamp": 1635287253328,
    "monorepository": true,
    "skipCommitHook": true,
    "jwtSecretKey": "ZjBkMjU1Y2JiMDlhMzI5YzM3NzAzMjQ1MDZiYTM2ODYzMjEzNjIzZTQzMjIxZGJhOGQzMzg4YjE2ZjM1OGNkZmI0NzNiOTYzYWY2NWU5YjI0ZWJkYzA4YTIxOTMwZGJjZDE1NjM1ZWE1ZjViOGUxY2JlODJjZWQyYzhmYWZiYTY=",
    "entities": ["Distribuidor", "Producto"],
    "lastLiquibaseTimestamp": 1635287373000
  }
}
