{
  "generator-jhipster": {
    "authenticationType": "jwt",
    "cacheProvider": "ehcache",
    "serverPort": "8082",
    "serviceDiscoveryType": "eureka",
    "skipUserManagement": true,
    "baseName": "microCarroDeCompras",
    "buildTool": "maven",
    "databaseType": "sql",
    "devDatabaseType": "mysql",
    "enableHibernateCache": true,
    "enableSwaggerCodegen": false,
    "enableTranslation": true,
    "jhiPrefix": "jhi",
    "languages": ["es", "en"],
    "messageBroker": false,
    "prodDatabaseType": "mysql",
    "searchEngine": false,
    "skipClient": true,
    "testFrameworks": [],
    "websocket": false,
    "enableGradleEnterprise": false,
    "gradleEnterpriseHost": "",
    "applicationType": "microservice",
    "packageName": "ar.edu.um.programacion2.micro_carro_de_compras",
    "packageFolder": "ar/edu/um/programacion2/micro_carro_de_compras",
    "nativeLanguage": "es",
    "jhipsterVersion": "7.3.0",
    "clientPackageManager": "npm",
    "dtoSuffix": "DTO",
    "entitySuffix": "",
    "reactive": false,
    "applicationIndex": 2,
    "gatewayServerPort": "9000",
    "skipServer": false,
    "skipCheckLengthOfIdentifier": false,
    "skipFakeData": false,
    "blueprints": [],
    "otherModules": [],
    "pages": [],
    "clientFramework": "angularX",
    "clientTheme": "none",
    "clientThemeVariant": "",
    "withAdminUi": false,
    "creationTimestamp": 1635287253327,
    "monorepository": true,
    "skipCommitHook": true,
    "jwtSecretKey": "ZTk1MjA5NTM0NWQyNWQ1Mjk0ODg3YzRmMzA2YzBhNDAxYWZjM2FlMDliNjg2MzZlOTJlMmU0OTU0ZWJlMzEyZDIyMGNjMGNiMDBjZDVjMzQ5YmY3OWEyYWIyZjg5NzBkOWMzODhlMzIzNzIyNDdhMzQzZjFmMzQwYzIyYjk0Mjc=",
    "entities": ["CarroCompra", "ProductoComprado", "ProductoSeleccionado", "Venta"],
    "lastLiquibaseTimestamp": 1635287493000
  }
}
